cicada_mcp_core/__init__.py
cicada_mcp_core/base_indexer.py
cicada_mcp_core/formatter_interface.py
cicada_mcp_core/utils/__init__.py
cicada_mcp_core/utils/hash_utils.py
cicada_mcp_core/utils/storage.py
cicada_mcp_core-0.1.0.dist-info/METADATA
cicada_mcp_core-0.1.0.dist-info/WHEEL
cicada_mcp_core-0.1.0.dist-info/RECORD
