Metadata-Version: 2.4
Name: cicada-mcp-core
Version: 0.1.0
Summary: Core utilities and interfaces for Cicada code intelligence
Author-email: wende <wende@hey.com>
License-Expression: MIT
Requires-Python: >=3.10
Provides-Extra: dev
Requires-Dist: pytest>=8.0; extra == 'dev'
Provides-Extra: yaml
Requires-Dist: pyyaml>=6.0; extra == 'yaml'
